fastrs/__init__.py
fastrs/_config/color_schemes.json
fastrs/_config/fasttext_defaults.json
fastrs/_config/plot_config.json
fastrs/_config/reduction_defaults.json
fastrs/core/exceptions.py
fastrs/core/object.py
fastrs/core/preprocessor.py
fastrs/core/util.py
fastrs/core/visualizer.py
simars-0.1.0.dist-info/METADATA
simars-0.1.0.dist-info/WHEEL
simars-0.1.0.dist-info/licenses/LICENSE
simars-0.1.0.dist-info/RECORD
