Metadata-Version: 2.4
Name: simars
Version: 0.1.0
Summary: FastText-based response similarity analyzer for human raters
Project-URL: Homepage, https://github.com/h000000nkim/fastrs
Project-URL: Repository, https://github.com/h000000nkim/fastrs
Project-URL: Documentation, https://h000000nkim.github.io/fastrs/
Author-email: Hoon Kim <h000000nkim@gmail.com>
License: MIT
License-File: LICENSE
Keywords: education,fasttext,jamo,korean,morphology,nlp,rater,similarity
Classifier: Development Status :: 4 - Beta
Classifier: Intended Audience :: Developers
Classifier: Intended Audience :: Education
Classifier: Intended Audience :: Science/Research
Classifier: License :: OSI Approved :: MIT License
Classifier: Operating System :: OS Independent
Classifier: Programming Language :: Python :: 3
Classifier: Programming Language :: Python :: 3 :: Only
Classifier: Programming Language :: Python :: 3.10
Classifier: Programming Language :: Python :: 3.11
Classifier: Programming Language :: Python :: 3.12
Classifier: Topic :: Education
Classifier: Topic :: Scientific/Engineering :: Artificial Intelligence
Classifier: Topic :: Text Processing :: Linguistic
Requires-Python: >=3.10
Requires-Dist: gensim>=4.3.3
Requires-Dist: hdbscan>=0.8.33
Requires-Dist: jamo>=0.4.1
Requires-Dist: numpy<2.0,>=1.26
Requires-Dist: pandas>=2.3.0
Requires-Dist: pecab>=1.0.8
Requires-Dist: plotly>=5.24
Requires-Dist: scikit-learn>=1.7.0
Requires-Dist: scipy<1.15,>=1.13
Requires-Dist: spacy<3.8,>=3.6
Requires-Dist: thinc<8.3,>=8.1
Requires-Dist: umap-learn>=0.5.6
Provides-Extra: dev
Requires-Dist: mkdocs-git-revision-date-localized-plugin>=1.2; extra == 'dev'
Requires-Dist: mkdocs-material>=9.5; extra == 'dev'
Requires-Dist: mkdocs-minify-plugin>=0.8; extra == 'dev'
Requires-Dist: mkdocstrings[python]>=0.26; extra == 'dev'
Requires-Dist: psutil>=6.0; extra == 'dev'
Requires-Dist: pytest-cov>=5.0; extra == 'dev'
Requires-Dist: pytest-mock>=3.14; extra == 'dev'
Requires-Dist: pytest>=8.3; extra == 'dev'
Requires-Dist: ruff>=0.6; extra == 'dev'
